{
  "completed": [
    "P0-A1",
    "P0-A2",
    "P0-A3",
    "P1-A1",
    "P1-A2",
    "P1-A3",
    "P1-A4",
    "P1-A5",
    "P2-A1",
    "P2-A2",
    "P2-A3",
    "P2-A4",
    "P2-A5",
    "P3-A1",
    "P3-A2",
    "P3-A3",
    "P3-A4",
    "P3-A5",
    "P3-A6",
    "P3-B1",
    "P3-B2",
    "P4-A1",
    "P4-A2",
    "P4-A3",
    "P4-A4",
    "P4-A4B",
    "P4-A5",
    "P4-A6",
    "P4-B1",
    "P4-B2",
    "P5-A1",
    "P5-A2",
    "P5-A3",
    "P5-A4",
    "P6-A1",
    "P6-A2",
    "P6-A3",
    "P6-A4",
    "P6-A5",
    "P6-A6",
    "P6-A7",
    "P6-B1",
    "P6-B2",
    "P6-C1",
    "P6-D1",
    "P7-A1",
    "P7-A2",
    "P7-A3",
    "P7-A4",
    "P7-A5",
    "P7-B1",
    "P7-C1",
    "P7-D1",
    "P7-D2",
    "P7-D3",
    "P7-D4",
    "P7-E1",
    "P7-E2",
    "P7-E3",
    "P7-F0",
    "P7-F1",
    "P7-F2",
    "P7-F3",
    "P7-F4",
    "P7-G1",
    "P7-G2a",
    "P7-G2b",
    "P7-G3",
    "P7-G4",
    "P8-A1",
    "P8-A2",
    "P8-A3",
    "P8-A4",
    "P900-A1",
    "P900-A2",
    "P900-A3",
    "P900-A4",
    "P900-A5",
    "P900-A6"
  ],
  "in_progress": "P900-A7",
  "plan_approved": true,
  "current_plan": "1. **Add tracing dependency.** Append `tracing = { workspace = true }` to `[dependencies]` in `crates/anvilml-ipc/Cargo.toml`. The workspace defines `tracing = \"0.1.44\"` in `[workspace.dependencies]` (confirmed at line 37 of root `Cargo.toml`).\n\n2. **Instrument `read_frame` PayloadTooLarge path.** In `framing.rs`, before the `return Err(AnvilError::PayloadTooLarge(...))` on line 46, insert:\n   ```rust\n   tracing::warn!(payload_mib = payload_len / 1024 / 1024, limit_mib = max_mib, \"IPC frame rejected: payload too large\");\n   ```\n   where `payload_len` is the variable holding `len as u64` (already in scope on line 45).\n\n3. **Instrument `read_frame` deserialize path.** On line 57\u201358, change the `.map_err(|e| AnvilError::Json(e.to_string()))?` to first log then error:\n   ```rust\n   let event = rmp_serde::from_slice::<WorkerEvent>(&payload).map_err(|e| {\n       tracing::error!(error = %e, \"IPC frame deserialize failed\");\n       AnvilError::Json(e.to_string())\n   })?;\n   ```\n\n4. **Instrument `write_frame` error paths.** On lines 15 and 18\u201319 of `write_frame`, add logging before each `.map_err(...)`. Specifically:\n   - Line 15 (msgpack serialization): the error is already caught by `.map_err`; wrap with a log:\n     ```rust\n     let payload = rmp_serde::to_vec_named(msg).map_err(|e| {\n         tracing::error!(error = %e, \"IPC frame write failed\");\n         AnvilError::Json(e.to_string())\n     })?;\n     ```\n   - Lines 18\u201319 (write_all header and payload): similarly wrap:\n     ```rust\n     w.write_all(&header).await.map_err(|e| {\n         tracing::error!(error = %e, \"IPC frame write failed\");\n         AnvilError::Io(e)\n     })?;\n     w.write_all(&payload).await.map_err(|e| {\n         tracing::error!(error = %e, \"IPC frame write failed\");\n         AnvilError::Io(e)\n     })?;\n     ```\n\n5. **Verify tests.** Run `cargo test -p anvilml-ipc` and confirm exit code 0 with no regressions. The existing test `read_frame_oversize_rejected` asserts on the error message string but does not assert log output, so it will continue to pass.",
  "failed": [],
  "needs_review": [],
  "last_updated": "2026-06-06T01:27:48+0200",
  "plan_approval_message_id": "1512598482920145058",
  "push_approval_message_id": null,
  "plan_report_message_id": "1512598479522762985",
  "impl_report_message_id": null
}